lilrsa/__init__.py
lilrsa/keygen.py
lilrsa-0.0.dist-info/LICENSE
lilrsa-0.0.dist-info/WHEEL
lilrsa-0.0.dist-info/METADATA
lilrsa-0.0.dist-info/RECORD
