Metadata-Version: 2.3
Name: lilrsa
Version: 0.0
Summary: Minimal RSA algorithm
Author-email: Elia Toselli <elia.toselli@outlook.it>
Classifier: License :: OSI Approved :: MIT License
Requires-Dist: sympy
Project-URL: Home, https://github.com/hilcon222/lilrsa
